{
  "project_info": {
    "project_number": "144175368903",
    "firebase_url": "https://ultrasonic-4466e-default-rtdb.firebaseio.com",
    "project_id": "ultrasonic-4466e",
    "storage_bucket": "ultrasonic-4466e.appspot.com"
  },
  "client": [
    {
      "client_info": {
        "mobilesdk_app_id": "1:144175368903:android:32456d75e032cbc544cce2",
        "android_client_info": {
          "package_name": "com.example.water_ui"
        }
      },
      "oauth_client": [
        {
          "client_id": "144175368903-1176cmb8r3dd7dds863ronjrm402hj7d.apps.googleusercontent.com",
          "client_type": 3
        }
      ],
      "api_key": [
        {
          "current_key": "AIzaSyBOrsqeNsWIAVcN_LWmXC2itapS7ZStROU"
        }
      ],
      "services": {
        "appinvite_service": {
          "other_platform_oauth_client": [
            {
              "client_id": "144175368903-1176cmb8r3dd7dds863ronjrm402hj7d.apps.googleusercontent.com",
              "client_type": 3
            }
          ]
        }
      }
    }
  ],
  "configuration_version": "1"
}